<list>

<line1>༄༅། །གསོལ་ཏོ། ། བཅོམ་ལྡན་འདས་གོའུ་ཏ་མའི་དཔལ་གྱིས་འཁོར་འདི་ཟིལ་གྱིས་གནོན་པར་མཛད་དོ། བཅོམ་ལྡན་འདས་གོའུ་མ་གཟི་བརྗིད་ཀྱིས་འཁོར་འདི་ཟིལ་གྱིས</line1>
<line2>གནོན་པར་མཛད་དོ། །བཅོམ་ལྡན་འདས་གེའུ་ཏ་མ་འོད་ཀྱིས་འཁོར་འདི་ཟིལ་གྱིས་གནོན་པར་མཛད་དདོ། ། བཅོམ་ལྡན་འདས་གོའུ་ཏ་མ་གཟུགས་ཀྱིས་འཁོར་འདི་ཟིལ་གྱིས་གནོན་པར</line2>
<line3>མཛད་དོ། ། བཅོམ་ལྡན་འདས་གོའུ་ཏ་མ་ནི་སྐུའི་ཁ་དོག་གསེར་ལྟ་བུའོ། །བཅོམ་ལྡན་འདས་གོའུ་ཏ་མ་ནི་སྐུ་གསེར་ལྟར་མཛེས་པའོ། ། བཅོམ་ལྡན་འདས་གོའུ་ཏ་མ་ནི་དངོས་པོ་ཐམས་ཅད་ཀྱིས</line3>
<line4>མི་མཉམ་པ་དང་མཉམ་པའོ། །བཅོམ་ལྡན་འདས་གོའུ་ཏ་མ་ནི་འཇིག་རྟེན་ཐམས་ཅད་ཀྱི་ང་མཚར་རྨད་དུ་བྱུང་བའི་ཆོས་དང་ལྡན་པ་ལགས་ན། བཅོམ་ལྡན་འདས་གོའུ་ཏ་མ་བདག་འདི་སྙམ་དུ</line4>
<line5>སེམས་ཏེ། བཅོམ་ལྡན་འདས་གོའུ་ཏམས་ཅི་ཞིག་གཟིགས་ནས་ཁབ་ནས་ཁབ་མ་མཆིས་པར་རབ་ཏུ་བྱུང་སྙམ་སེམས་སོ། ། དེ་ནས་བཅོམ་ལྡན་འདས་ལ། ཁྱིམ་བདག་ཚོང་</line5>
<line6>དཔོན་བཟང་སྐྱོང་གིས་ཚིགས་སུ་བཅད་པ་འདི་དག་གིས་མངོན་པར་བསྟོད་དོ། ། རྒྱལ་བའི་དཔལ་དང་གྲགས་དང་གཟུགས་དག་ནི། །སྔན་ཆད་བདག་གིས་ཇི་སྐད་ཐོས་པ་བས། ། དེ་བས་ལྷག</line6>
<line7>པར་གསེར་གྱི་གཟུགས་བཞིན་དུ། །མཛེས་དང་ལྡན་པར་ལྷམ་མེར་རབ་ཏུ་གདའ། །གཟུགས་ནི་ཤིན་ཏུ་མཛེས་ཤིང་བལྟ་ན་སྡུག །སྐུ་ཡི་ཁ་དོག་གསེར་གྱི་མདོག་འདྲ་བས། །སྐར་མ་དག་གི</line7>

<err>1</err>
</list>