<list>

<line1>༄༅། །གང་ལའང་མི་དགའ་སྟེ། ཉོན་མོངས་མེད་པ་འདུས་མ་བྱས། ། མྱ་ངན་འདས་པ་ཐོབ་པར་བྱ། །གཞན་ཡང་ཀྱེ་མའོ་ཁྱིམ་བདག་འཇིག་རྟེན་གནས</line1>
<line2>པ་འདི་ནི། འདི་ལྟ་སྟེ། ཕྲག་དོག་དང་སེར་སྣའི་ཀུན་ཏུ་སྦྱོར་བ་དང་ལྡན་པར་ཤེས། ཀྱེ་མའོ་ཁྱིམ་བདག་འཇིག་རྟེན་གནས་པ་འདི་ནི། འདི་ལྟ་སྟེ། མ་རིག་པའི་ལིང་ཏོག་གིས་ཁེབས་པར</line2>
<line3>མཐོང་། ཀྱེ་མའོ་ཁྱིམ་བདག་འཇིག་རྟེན་གནས་པ་འདི་ནི། འདི་ལྟ་སྟེ། གཏི་མུག་གི་འོབས་སུ་ནུབ་པར་མཐོང་། ཀྱེ་མའོ་ཁྱིམ་བདག་འཇིག་རྟེན་གནས་པ་འདི་ནི། འདི་ལྟ་སྟེ། འདོད</line3>
<line4>པའི་ཀླུང་གིས་དེད་པར་མཐོང་། ཀྱེ་སའོ་ཁྱིམ་བདག་འཇིག་རྟེན་གནས་པ་འདི་ནི། འདི་ལྟ་སྟེ། འདོད་པའི་ཟུག་རྡུས་གཤིས་སུ་ཟུག་པར་མཐོང་། ཀྱེ་མའོ་ཁྱིམ་བདག་འཇིག་རྟེན་གནས</line4>
<line5>བ་འདི་ནི། འདི་ལྟ་སྟེ། ཁྲོ་བ་དང་ཁོན་དུ་འཛིན་པའི་དུ་བས་ཤིན་ཏུ་བདུགས་པར་མཐོང་། ཀྱེ་མའོ་ཁྱིམ་བདག་འཇིག་རྟེན་གནས་པ་འདི་ནི། འདི་ལྟ་སྟེ། འདོད་ཆགས་ཀྱི་མེས་ཀུན་ཏུ་འབར</line5>
<line6>བར་མཐོང་། ཀྱེ་མའོ་ཁྱིམ་བདག་འཇིག་རྟེན་གནས་པ་འདི་ནི། འདི་ལྟ་སྟེ། ཞེ་སྡང་གི་དུག་གིས་ཀུན་ཏུ་ཁེབས་པར་མཐོང་། ཀྱེ་མའོ་ཁྱིམ་བདག་འཇིག་རྟེན་གནས་པ་འདི་ནི་འདི་ལྟ་སྟེ། </line6>
<line7>སྒྲིབ་པའི་ཚེར་མས་བསྐོར་བར་མཐོང་། ཀྱེ་མའོ་ཁྱིམ་བདག་འཇིག་རྟེན་གནས་པ་འདི་ནི། འདི་ལྟ་སྟེ། འཁོའ་བའི་འབྲོག་དགོན་པར་བརྩོན་འགྲུས་ཉམས་པར་མཐོང་སྟེ། ཁྱིམ་བདག་འཇིག</line7>

<err>1</err>
</list>